XFIN/__init__.py
XFIN/app.py
XFIN/cli.py
XFIN/compliance.py
XFIN/credit_risk.py
XFIN/explainer.py
XFIN/utils.py
xfin_xai-0.1.2.dist-info/METADATA
xfin_xai-0.1.2.dist-info/WHEEL
xfin_xai-0.1.2.dist-info/entry_points.txt
xfin_xai-0.1.2.dist-info/top_level.txt
xfin_xai-0.1.2.dist-info/RECORD
