Metadata-Version: 2.4
Name: xfin-xai
Version: 0.1.2
Summary: Privacy-Preserving Explainable AI Library for Financial Services and Banking Systems
Home-page: https://github.com/dhruvparmar10/XFIN
Author: Rishabh Bhangale & Dhruv Parmar
Author-email: dhruv.jparmar0@gmail.com
License: MIT
Project-URL: Bug Reports, https://github.com/dhruvparmar10/XFIN/issues
Project-URL: Source, https://github.com/dhruvparmar10/XFIN
Project-URL: Documentation, https://github.com/dhruvparmar10/XFIN/blob/main/README.md
Keywords: explainable-ai,finance,privacy,machine-learning,credit-risk,compliance
Classifier: Development Status :: 1 - Planning
Classifier: Intended Audience :: Developers
Classifier: Intended Audience :: Financial and Insurance Industry
Classifier: Intended Audience :: Science/Research
Classifier: Topic :: Scientific/Engineering :: Artificial Intelligence
Classifier: Topic :: Office/Business :: Financial
Classifier: License :: OSI Approved :: MIT License
Classifier: Programming Language :: Python :: 3.9
Classifier: Programming Language :: Python :: 3.10
Classifier: Programming Language :: Python :: 3.11
Requires-Python: >=3.9
Requires-Dist: streamlit
Requires-Dist: pandas
Requires-Dist: joblib
Requires-Dist: shap
Requires-Dist: lime
Requires-Dist: numpy
Requires-Dist: matplotlib
Requires-Dist: requests
Requires-Dist: python-dotenv
Requires-Dist: scikit-learn
Provides-Extra: dev
Requires-Dist: pytest; extra == "dev"
Requires-Dist: black; extra == "dev"
Requires-Dist: flake8; extra == "dev"
Dynamic: author
Dynamic: author-email
Dynamic: classifier
Dynamic: description
Dynamic: description-content-type
Dynamic: home-page
Dynamic: keywords
Dynamic: license
Dynamic: project-url
Dynamic: provides-extra
Dynamic: requires-dist
Dynamic: requires-python
Dynamic: summary
